hud_vf_gym/__init__.py
hud_vf_gym/hud_vf_gym.py
hud_vf_gym/mcp_utils.py
hud_vf_gym/parsers.py
hud_vf_gym/rubrics.py
hud_vf_gym-0.1.1.dist-info/METADATA
hud_vf_gym-0.1.1.dist-info/WHEEL
hud_vf_gym-0.1.1.dist-info/licenses/LICENSE
hud_vf_gym-0.1.1.dist-info/RECORD
