Metadata-Version: 2.4
Name: hud-vf-gym
Version: 0.1.1
Summary: HUD environments for Reinforcement Learning through Verifiers
License-File: LICENSE
Requires-Python: >=3.12
Requires-Dist: hud-python[agent]
Requires-Dist: verifiers>=0.1.3
